molgroups/__init__.py
molgroups/components.py
molgroups/lipids.py
molgroups/mol.py
molgroups-0.2.0a0.dist-info/LICENSE
molgroups-0.2.0a0.dist-info/METADATA
molgroups-0.2.0a0.dist-info/WHEEL
molgroups-0.2.0a0.dist-info/top_level.txt
molgroups-0.2.0a0.dist-info/RECORD
