Metadata-Version: 2.1
Name: molgroups
Version: 0.2.0a0
Summary: Molecular Modeling for Scattering Data Analysis
Home-page: https://github.com/criosx/molgroups
Author: Frank Heinrich, David Hoogerheide, Alyssa Thomas
Author-email: mail@frank-heinrich.net
License: MIT License
License-File: LICENSE
Requires-Dist: bumps
Requires-Dist: refl1d
Requires-Dist: periodictable
Requires-Dist: scipy
Requires-Dist: numpy
Requires-Dist: matplotlib
Requires-Dist: pandas
Requires-Dist: scikit-learn
Requires-Dist: sasmodels
Requires-Dist: sasdata
Requires-Dist: dill
